{
  "preguntas": [
    {
      "id": "pregunta1",
      "pregunta": "¿Cuál es la capital de Francia?",
      "respuestas": ["Londres", "Madrid", "Berlín", "París"],
      "respuesta_correcta": "París",
      "dificultad": 1
    },
    {
      "id": "pregunta1",
      "pregunta": "Membranas móviles cubiertas de piel que resguardan los ojos:",
      "respuestas": ["Cejas", "Párpados", "Pupilas", "Pestañas"],
      "respuesta_correcta": "Párpados",
      "dificultad": 1
    },
    {
      "id": "pregunta1",
      "pregunta": "¿Cuál es la Supernena de color azul?",
      "respuestas": ["Pétalo", "Mojo-Yoyo", "Burbuja", "Cactus"],
      "respuesta_correcta": "Burbuja",
      "dificultad": 1
    },
    {
      "id": "pregunta2",
      "pregunta": "¿Cuál es la fórmula química del agua?",
      "respuestas": ["H2O", "CO2", "NaCI", "C6H12O6"],
      "respuesta_correcta": "H2O",
      "dificultad": 2
    },
    {
      "id": "pregunta2",
      "pregunta": "¿Qué pokémon acompaña siempre a Ash Ketchum?",
      "respuestas": ["Charmander", "Pikachu", "Squirtle", "Pichu"],
      "respuesta_correcta": "Pikachu",
      "dificultad": 2
    },
    {
      "id": "pregunta2",
      "pregunta": "¿Cual NO es una raza de perro?",
      "respuestas": ["Chiguagua", "Pastor Alemán", "Perro Esponjoso Aéreo", "San Bernardo"],
      "respuesta_correcta": "Perro Esponjoso Aéreo",
      "dificultad": 2
    },
    {
      "id": "pregunta3",
      "pregunta": "¿Cuál de estas películas dirigió Tim Burton?",
      "respuestas": ["Men in Black", "Pesadilla antes de Navidad", "Big Fish", "Yo Robot"],
      "respuesta_correcta": "Big Fish",
      "dificultad": 3
    },
    {
      "id": "pregunta3",
      "pregunta": "¿Qué personaje NO pertenece al juego League of Legends?",
      "respuestas": ["Lux", "Tryndamere", "Toadette", "Miss Fortune"],
      "respuesta_correcta": "Toadette",
      "dificultad": 3
    },
    {
      "id": "pregunta3",
      "pregunta": "¿Cuántos balones de oro tiene Messi?",
      "respuestas": ["5", "7", "3", "4"],
      "respuesta_correcta": "7",
      "dificultad": 3
    },
    {
      "id": "pregunta4",
      "pregunta": "¿Cuál es el océano más grande del mundo?",
      "respuestas": ["Océano Pacífico", "Océano Atlántico", "Océano Índico", "Océano Ártico"],
      "respuesta_correcta": "Océano Pacífico",
      "dificultad": 4
    },
    {
      "id": "pregunta4",
      "pregunta": "¿Quién es M.Rajoy?",
      "respuestas": ["Murcia Rajoy", "Manoj Rajoy", "Mariano Rajoy", "Mario Rajoy"],
      "respuesta_correcta": "Mariano Rajoy",
      "dificultad": 4
    },
    {
      "id": "pregunta4",
      "pregunta": "¿Cuál de los siguientes pintores era también arquitecto?",
      "respuestas": ["Vincent van Goh", "Pablo Picasso", "Michelangelo", "Leonardo da Vinci"],
      "respuesta_correcta": "Leonardo da Vinci",
      "dificultad": 4
    },
    {
      "id": "pregunta5",
      "pregunta": "¿Cuál es el autor de la novela 'Cien años de soledad'?",
      "respuestas": ["Gabriel García Márquez", "Pablo Neruda", "Jorge Luis Borges", "Mario Vargas Llosa"],
      "respuesta_correcta": "Gabriel García Márquez",
      "dificultad": 5
    },
    {
      "id": "pregunta5",
      "pregunta": "¿En qué año se estrenó la película 'Titanic', dirigida por James Cameron en EEUU?",
      "respuestas": ["1996", "1997", "1998", "1999"],
      "respuesta_correcta": "1997",
      "dificultad": 5
    },
    {
      "id": "pregunta5",
      "pregunta": "¿Cuál es el evento deportivo más importante a nivel mundial en el deporte del fútbol?",
      "respuestas": ["Copa Mundial de la FIFA", "Juegos Olímpicos", "Copa América", "UEFA Champions League"],
      "respuesta_correcta": "Copa Mundial de la FIFA",
      "dificultad": 5
    },
    {
      "id": "pregunta6",
      "pregunta": "¿Cuál de los siguientes escritores no es conocido por escribir obras de ciencia ficción?",
      "respuestas": ["H.G. Wells", "Isaac Asimov", "Arthur C. Clarke", "Ernest Hemingway"],
      "respuesta_correcta": "Isaac Asimov",
      "dificultad": 6
    },
    {
      "id": "pregunta6",
      "pregunta": "¿Cuál de las siguientes enfermedades es causada por un virus?",
      "respuestas": ["Malaria", "Tuberculosis", "Sarampión", "Diabetes"],
      "respuesta_correcta": "Sarampión",
      "dificultad": 6
    },
    {
      "id": "pregunta6",
      "pregunta": "¿Qué es el ébano?",
      "respuestas": ["Un mineral", "Un animal", "Una madera", "Una tela"],
      "respuesta_correcta": "Una madera",
      "dificultad": 6
    },
    {
      "id": "pregunta7",
      "pregunta": "¿En qué juego hace su primera aparición Leon Kennedy en la saga de Resident Evil?",
      "respuestas": ["Resident Evil", "Resident Evil 4", "Resident Evil 2", "Resident Evil: Code Veronica"],
      "respuesta_correcta": "Resident Evil 2",
      "dificultad": 7
    },
    {
      "id": "pregunta7",
      "pregunta": "¿En qué año se creó el famoso programa español Grand Prix?",
      "respuestas": ["1992", "1998", "1995", "2001"],
      "respuesta_correcta": "1995",
      "dificultad": 7
    },
    {
      "id": "pregunta7",
      "pregunta": "¿Qué es el ornitorrinco?",
      "respuestas": ["Mamífero", "Vivíparo", "Ave", "Anfibio"],
      "respuesta_correcta": "Mamífero",
      "dificultad": 7
    },
    {
      "id": "pregunta8",
      "pregunta": "¿Cuál es el nombre completo del futbolista Cristiano Ronaldo?",
      "respuestas": ["Cristiano Ronaldo los Santos Diego", "Cristiano Ronaldo dos Santos Aveiro", "Cristiano Ronaldo Armando Diego Ronaldo", "Cristiano Ronaldo Luis Armando Ronaldo"],
      "respuesta_correcta": "Cristiano Ronaldo dos Santos Aveiro",
      "dificultad": 8
    },
    {
      "id": "pregunta8",
      "pregunta": "¿Cuál es el nombre de la hija de Kratos en God of War?",
      "respuestas": ["Ellie", "Atreus", "Perséfone", "Calíope"],
      "respuesta_correcta": "Calíope",
      "dificultad": 8
    },
    {
      "id": "pregunta8",
      "pregunta": "¿Cuál fue la primera consola lanzada por Nintendo?",
      "respuestas": ["GameBoy", "Nintendo 64", "Nintendo DS", "NES"],
      "respuesta_correcta": "NES",
      "dificultad": 8
    },
    {
      "id": "pregunta9",
      "pregunta": "¿Cuál es el animal más rápido del mundo?",
      "respuestas": ["Leopardo", "Guepardo", "Lobo", "Jaguar"],
      "respuesta_correcta": "Guepardo",
      "dificultad": 9
    },
    {
      "id": "pregunta9",
      "pregunta": "¿Cuál de las siguientes películas ganó el Premio Óscar a Mejor Película en el año 2019?",
      "respuestas": ["La La Land", "Guepardo", "El renacido", "Moonlight"],
      "respuesta_correcta": "Moonlight",
      "dificultad": 9
    },
    {
      "id": "pregunta9",
      "pregunta": "¿En qué año se inauguró el Museo del Louvre en París?",
      "respuestas": ["1776", "1793", "1821", "1889"],
      "respuesta_correcta": "1793",
      "dificultad": 9
    },
    {
      "id": "pregunta10",
      "pregunta": "¿Cómo se llama la radiación emitida por los agujeros negros?",
      "respuestas": ["Radiación Hawking", "Radiación Ganma", "Radiación Electromagnética", "Radiación Nuclear"],
      "respuesta_correcta": "Radiación Hawking",
      "dificultad": 10
    },
    {
      "id": "pregunta10",
      "pregunta": "¿Cuál es el metal más ligero en la Tierra?",
      "respuestas": ["Litio", "Aluminio", "Titanio", "Magnesio"],
      "respuesta_correcta": "Litio",
      "dificultad": 10
    },
    {
      "id": "pregunta10",
      "pregunta": "¿Cuál es el planeta del sistema solar más caliente?",
      "respuestas": ["Mercurio", "Venus", "Júpiter", "Neptuno"],
      "respuesta_correcta": "Venus",
      "dificultad": 10
    },
    {
      "id": "pregunta11",
      "pregunta": "¿Cuál es la lengua más hablada del mundo?",
      "respuestas": ["Español", "Inglés", "Mandarín", "Hindi"],
      "respuesta_correcta": "Mandarín",
      "dificultad": 11
    },
    {
      "id": "pregunta11",
      "pregunta": "¿Cuál es la molécula responsable del transporte de oxígeno en la sangre de los vertebrados?",
      "respuestas": ["Hemoglobina", "Clorofila", "Insulina", "Mioglobina"],
      "respuesta_correcta": "Hemoglobina",
      "dificultad": 11
    },
    {
      "id": "pregunta11",
      "pregunta": "¿Cuál es la hormona responsable de regular el metabolismo en el cuerpo humano?",
      "respuestas": ["Insulina", "Adrenalina", "Tiroxina", "Melatonina"],
      "respuesta_correcta": "Tiroxina",
      "dificultad": 11
    },
    {
      "id": "pregunta12",
      "pregunta": "¿Cuál es el órgano más grande del cuerpo humano?",
      "respuestas": ["Hígado", "Piel", "Pulmón", "Corazón"],
      "respuesta_correcta": "Piel",
      "dificultad": 12
    },
    {
      "id": "pregunta12",
      "pregunta": "¿Qué científico desarrolló la teoría de la relatividad?",
      "respuestas": ["Isaac Newton", "Albert Einstein", "Galileo Galilei", "Charles Darwin"],
      "respuesta_correcta": "Albert Einstein",
      "dificultad": 12
    },
    {
      "id": "pregunta12",
      "pregunta": "¿Cuál es el río más largo del mundo?",
      "respuestas": ["Nilo", "Amazonas", "Yangtsé", "Mississippi"],
      "respuesta_correcta": "Amazonas",
      "dificultad": 12
    },
    {
      "id": "pregunta13",
      "pregunta": "¿Cuál es el metal más abundante en la corteza terrestre?",
      "respuestas": ["Hierro", "Aluminio", "Cobre", "Plomo"],
      "respuesta_correcta": "Aluminio",
      "dificultad": 13
    },
    {
      "id": "pregunta13",
      "pregunta": "¿Cuál es la montaña más alta del mundo?",
      "respuestas": ["Monte Kilimanjaro", "Monte McKinley", "Monte Everest", "Montaña Aconcagua"],
      "respuesta_correcta": "Monte Everest",
      "dificultad": 13
    },
    {
      "id": "pregunta13",
      "pregunta": "¿Quién fue la primera programadora de la historia?",
      "respuestas": ["Grace Hopper", "Ada Lovelace", "Margaret Hamilton", "Alan Turing"],
      "respuesta_correcta": "Ada Lovelace",
      "dificultad": 13
    },
    {
      "id": "pregunta14",
      "pregunta": "¿Cuál es el país más grande del mundo en términos de superficie terrestre?",
      "respuestas": ["Estados Unidos", "China", "Rusia", "Andorra la Vella"],
      "respuesta_correcta": "Rusia",
      "dificultad": 14
    },
    {
      "id": "pregunta14",
      "pregunta": "¿Cuál es la capital de Australia?",
      "respuestas": ["Melbourne", "Canberra", "Madrid", "Sídney"],
      "respuesta_correcta": "Canberra",
      "dificultad": 14
    },
    {
      "id": "pregunta14",
      "pregunta": " ¿Cuál es la novela más vendida de todos los tiempos?",
      "respuestas": ["Harry Potter y la Piedra Filosofal", "El Principito", "La historia de Adobe Campaign", "Don Quijote de la Mancha"],
      "respuesta_correcta": "Don Quijote de la Mancha",
      "dificultad": 14
    },
    {
      "id": "Pregunta15",
      "pregunta": "¿Quién pintó la obra La última cena?",
      "respuestas": ["Jeanine Murcia Picasso", "Leonardo da Vinci", "Vincent van Gogh", "Luigi da Vinci"],
      "respuesta_correcta": "Leonardo da Vinci",
      "dificultad": 15
    },
    {
      "id": "Pregunta15",
      "pregunta": " ¿Cuál es la obra más famosa del compositor Ludwig van Beethoven?",
      "respuestas": ["Sinfonía No. 5", "Sinfonía No. 9 (Coral)", "Himno de Ntt Data", "Für Elise"],
      "respuesta_correcta": "Sinfonía No. 9 (Coral)",
      "dificultad": 15
    },
    {
      "id": "Pregunta15",
      "pregunta": "¿Cuál es el nombre del actor que interpretó a Severus Snape en las películas de Harry Potter?",
        "respuestas": ["Ralph Fiennes", "Hector el Malo", "Daniel Radcliffe", "Alan Rickman"],
      "respuesta_correcta": "Alan Rickman",
      "dificultad": 15
    }
  ]
}